<level name="Level 5" map="g6_5a" difficulty="hard" type="advanced" time="120">
	<blocks>
		<block type="one-laser_source" fixedposition="true">
			<position x="16" y="1"/>
		</block>
		<block type="two-laser-middle-oriented_target" fixedposition="true" fixedorientation="true" orientation="RIGHT">
			<position x="3" y="17"/>
		</block>
		<block type="blocker" fixedposition="true" fixedorientation="true">
			<position x="16" y="5"/>
		</block>
		<block type="blocker" fixedposition="true" fixedorientation="true">
			<position x="6" y="1"/>
		</block>
		<block type="blocker" fixedposition="true" fixedorientation="true">
			<position x="13" y="16"/>
		</block>
		<block type="two-way-big-angled_splitter" fixedposition="true">
			<position x="13" y="4"/>
		</block>
		<block type="blocker"/>
		<block type="blocker"/>
		<block type="blocker"/>
		<block type="blocker"/>
		<block type="one-way_mirror"/>
		<block type="one-way_mirror"/>
		<block type="one-way_mirror"/>
		<block type="one-way-oriented_mirror"/>
		<block type="one-way-oriented_mirror"/>
		<block type="one-way-oriented_mirror"/>
		<block type="two-way_mirror"/>
		<block type="two-way_mirror"/>
	</blocks>
</level>
